odoo10_addon_account_invoice_import_invoice2data-10.0.1.0.1-py2.7-nspkg.pth
odoo/addons/account_invoice_import_invoice2data/README.rst
odoo/addons/account_invoice_import_invoice2data/__init__.py
odoo/addons/account_invoice_import_invoice2data/__manifest__.py
odoo/addons/account_invoice_import_invoice2data/demo/demo_data.xml
odoo/addons/account_invoice_import_invoice2data/i18n/sl.po
odoo/addons/account_invoice_import_invoice2data/tests/__init__.py
odoo/addons/account_invoice_import_invoice2data/tests/test_invoice_import.py
odoo/addons/account_invoice_import_invoice2data/tests/pdf/invoice_free_fiber_201507.pdf
odoo/addons/account_invoice_import_invoice2data/wizard/__init__.py
odoo/addons/account_invoice_import_invoice2data/wizard/account_invoice_import.py
odoo10_addon_account_invoice_import_invoice2data-10.0.1.0.1.dist-info/DESCRIPTION.rst
odoo10_addon_account_invoice_import_invoice2data-10.0.1.0.1.dist-info/METADATA
odoo10_addon_account_invoice_import_invoice2data-10.0.1.0.1.dist-info/RECORD
odoo10_addon_account_invoice_import_invoice2data-10.0.1.0.1.dist-info/WHEEL
odoo10_addon_account_invoice_import_invoice2data-10.0.1.0.1.dist-info/metadata.json
odoo10_addon_account_invoice_import_invoice2data-10.0.1.0.1.dist-info/namespace_packages.txt
odoo10_addon_account_invoice_import_invoice2data-10.0.1.0.1.dist-info/top_level.txt
